Workbook

Sheet 📋 Lançamentos
A1: 🍽️ RESTAURANTE SABOR DE CASA — LANÇAMENTOS FINANCEIROS 2024
A2: Data | B2: Mês | C2: Categoria | D2: Subcategoria | E2: Tipo | F2: Descrição | G2: Qtd/Unid | H2: Valor Unit. (R$) | I2: Valor Total (R$)
A3: 2024-01-10 | B3: Janeiro | C3: Vendas Salão | D3: Pratos Principais | E3: Receita | F3: Venda de pratos principais (almoço/jantar) | G3: 331 | H3: 58 | I3: =G3*H3 -> 19198
A4: 2024-01-10 | B4: Janeiro | C4: Vendas Salão | D4: Entradas e Petiscos | E4: Receita | F4: Venda de entradas e petiscos | G4: 228 | H4: 24 | I4: =G4*H4 -> 5472
A5: 2024-01-05 | B5: Janeiro | C5: Vendas Salão | D5: Sobremesas | E5: Receita | F5: Venda de sobremesas | G5: 161 | H5: 18 | I5: =G5*H5 -> 2898
A6: 2024-01-20 | B6: Janeiro | C6: Bebidas | D6: Drinks e Coquetéis | E6: Receita | F6: Venda de drinks e coquetéis artesanais | G6: 238 | H6: 32 | I6: =G6*H6 -> 7616
A7: 2024-01-28 | B7: Janeiro | C7: Bebidas | D7: Vinhos e Cervejas | E7: Receita | F7: Venda de vinhos e cervejas importadas | G7: 145 | H7: 55 | I7: =G7*H7 -> 7975
A8: 2024-01-25 | B8: Janeiro | C8: Bebidas | D8: Não Alcoólicas | E8: Receita | F8: Sucos, refrigerantes e água | G8: 322 | H8: 12 | I8: =G8*H8 -> 3864
A9: 2024-01-20 | B9: Janeiro | C9: Delivery | D9: iFood/Rappi | E9: Receita | F9: Pedidos via plataformas de delivery | G9: 415 | H9: 47 | I9: =G9*H9 -> 19505
A10: 2024-01-25 | B10: Janeiro | C10: Delivery | D10: Delivery Próprio | E10: Receita | F10: Pedidos via app próprio do restaurante | G10: 149 | H10: 52 | I10: =G10*H10 -> 7748
A11: 2024-01-15 | B11: Janeiro | C11: Eventos | D11: Festas Privadas | E11: Receita | F11: Aluguel de espaço para eventos privados | G11: 3 | H11: 1800 | I11: =G11*H11 -> 5400
A12: 2024-01-28 | B12: Janeiro | C12: Eventos | D12: Happy Hour Empresa | E12: Receita | F12: Pacotes happy hour corporativo | G12: 5 | H12: 650 | I12: =G12*H12 -> 3250
A13: 2024-01-20 | B13: Janeiro | C13: CMV | D13: Carnes e Proteínas | E13: Despesa | F13: Compra de carnes, frutos do mar e proteínas | G13: 1 | H13: 14381.55 | I13: =G13*H13 -> 14381.55
A14: 2024-01-25 | B14: Janeiro | C14: CMV | D14: Hortifrúti | E14: Despesa | F14: Verduras, legumes e frutas | G14: 1 | H14: 4213.44 | I14: =G14*H14 -> 4213.44
... A386: 2024-12-20 | B386: Dezembro | C386: Taxas/Impostos | D386: Alvará e Licenças | E386: Despesa | F386: Renovação de alvarás e taxas municipais | G386: 1 | H386: 378.75 | I386: =G386*H386 -> 378.75
A387: TOTAL GERAL | I387: =SUMIF(E3:E386,"Receita",I3:I386)-SUMIF(E3:E386,"Despesa",I3:I386) -> 38244.46
A389: 💡 Dica: Use os filtros da linha 2 para analisar por Mês, Categoria ou Tipo. Valores na coluna I são calculados automaticamente (Qtd × Valor Unit.).

Sheet 📊 DRE Mensal
A1: 📊 DEMONSTRAÇÃO DO RESULTADO DO EXERCÍCIO (DRE) — 2024
B3: Jan | C3: Fev | D3: Mar | E3: Abr | F3: Mai | G3: Jun | H3: Jul | I3: Ago | J3: Set | K3: Out | L3: Nov | M3: Dez | N3: TOTAL
A4: ▶ RECEITAS BRUTAS
A5: Vendas Salão | B5: {=SUMPRODUCT(('📋 Lançamentos'!$B$3:$B$386="Janeiro")*('📋 Lançamentos'!$E$3:$E$386="Receita")*('📋 Lançamentos'!$C$3:$C$386="Vendas Salão"),'📋 Lançamentos'!$I$3:$I$386)} -> 27568 | C5: {=SUMPRODUCT(('📋 Lançamentos'!$B$3:$B$386="Fevereiro")*('📋 Lançamentos'!$E$3:$E$386="Receita")*('📋 Lançamentos'!$C$3:$C$386="Vendas Salão"),'📋 Lançamentos'!$I$3:$I$386)} -> 28418 | D5: {=SUMPRODUCT(('📋 Lançamentos'!$B$3:$B$386="Março")*('📋 Lançamentos'!$E$3:$E$386="Receita")*('📋 Lançamentos'!$C$3:$C$386="Vendas Salão"),'📋 Lançamentos'!$I$3:$I$386)} -> 32482 | E5: {=SUMPRODUCT(('📋 Lançamentos'!B$3:B$386="Abril")*('📋 Lançamentos'!E$3:E$386="Receita")*('📋 Lançamentos'!C$3:C$386="Vendas Salão"),'📋 Lançamentos'!I$3:I$386)} -> 36752 | F5: {=SUMPRODUCT(('📋 Lançamentos'!B$3:B$386="Maio")*('📋 Lançamentos'!E$3:E$386="Receita")*('📋 Lançamentos'!C$3:C$386="Vendas Salão"),'📋 Lançamentos'!I$3:I$386)} -> 37384 | G5: {=SUMPRODUCT(('📋 Lançamentos'!B$3:B$386="Junho")*('📋 Lançamentos'!E$3:E$386="Receita")*('📋 Lançamentos'!C$3:C$386="Vendas Salão"),'📋 Lançamentos'!I$3:I$386)} -> 40256 | H5: {=SUMPRODUCT(('📋 Lançamentos'!B$3:B$386="Julho")*('📋 Lançamentos'!E$3:E$386="Receita")*('📋 Lançamentos'!C$3:C$386="Vendas Salão"),'📋 Lançamentos'!I$3:I$386)} -> 42388 | I5: {=SUMPRODUCT(('📋 Lançamentos'!B$3:B$386="Agosto")*('📋 Lançamentos'!E$3:E$386="Receita")*('📋 Lançamentos'!C$3:C$386="Vendas Salão"),'📋 Lançamentos'!I$3:I$386)} -> 39418 | J5: {=SUMPRODUCT(('📋 Lançamentos'!B$3:B$386="Setembro")*('📋 Lançamentos'!E$3:E$386="Receita")*('📋 Lançamentos'!C$3:C$386="Vendas Salão"),'📋 Lançamentos'!I$3:I$386)} -> 35494 | K5: {=SUMPRODUCT(('📋 Lançamentos'!B$3:B$386="Outubro")*('📋 Lançamentos'!E$3:E$386="Receita")*('📋 Lançamentos'!C$3:C$386="Vendas Salão"),'📋 Lançamentos'!I$3:I$386)} -> 37566 | L5: {=SUMPRODUCT(('📋 Lançamentos'!B$3:B$386="Novembro")*('📋 Lançamentos'!E$3:E$386="Receita")*('📋 Lançamentos'!C$3:C$386="Vendas Salão"),'📋 Lançamentos'!I$3:I$386)} -> 40356 | M5: {=SUMPRODUCT(('📋 Lançamentos'!B$3:B$386="Dezembro")*('📋 Lançamentos'!E$3:E$386="Receita")*('📋 Lançamentos'!C$3:C$386="Vendas Salão"),'📋 Lançamentos'!I$3:I$386)} -> 49238 | N5: =SUM(B5:M5) -> 447320
A6: Bebidas | B6: {=SUMPRODUCT(('📋 Lançamentos'!$B$3:$B$386="Janeiro")*('📋 Lançamentos'!$E$3:$E$386="Receita")*('📋 Lançamentos'!$C$3:$C$386="Bebidas"),'📋 Lançamentos'!$I$3:$I$386)} -> 19455 | C6: {=SUMPRODUCT(('📋 Lançamentos'!$B$3:$B$386="Fevereiro")*('📋 Lançamentos'!$E$3:$E$386="Receita")*('📋 Lançamentos'!$C$3:$C$386="Bebidas"),'📋 Lançamentos'!$I$3:$I$386)} -> 20270 | D6: {=SUMPRODUCT(('📋 Lançamentos'!$B$3:$B$386="Março")*('📋 Lançamentos'!$E$3:$E$386="Receita")*('📋 Lançamentos'!$C$3:$C$386="Bebidas"),'📋 Lançamentos'!$I$3:$I$386)} -> 22647 | E6: {=SUMPRODUCT(('📋 Lançamentos'!$B$3:$B$386="Abril")*('📋 Lançamentos'!$E$3:$E$386="Receita")*('📋 Lançamentos'!$C$3:$C$386="Bebidas"),'📋 Lançamentos'!$I$3:$I$386)} -> 25328 | F6: {=SUMPRODUCT(('📋 Lançamentos'!$B$3:$B$386="Maio")*('📋 Lançamentos'!$E$3:$E$386="Receita")*('📋 Lançamentos'!$C$3:$C$386="Bebidas"),'📋 Lançamentos'!$I$3:$I$386)} -> 25634 | G6: {=SUMPRODUCT(('📋 Lançamentos'!$B$3:$B$386="Junho")*('📋 Lançamentos'!$E$3:$E$386="Receita")*('📋 Lançamentos'!$C$3:$C$386="Bebidas"),'📋 Lançamentos'!$I$3:$I$386)} -> 28029 | H6: {=SUMPRODUCT(('📋 Lançamentos'!$B$3:$B$386="Julho")*('📋 Lançamentos'!$E$3:$E$386="Receita")*('📋 Lançamentos'!$C$3:$C$386="Bebidas"),'📋 Lançamentos'!$I$3:$I$386)} -> 26653 | I6: {=SUMPRODUCT(('📋 Lançamentos'!$B$3:$B$386="Agosto")*('📋 Lançamentos'!$E$3:$E$386="Receita")*('📋 Lançamentos'!$C$3:$C$386="Bebidas"),'📋 Lançamentos'!$I$3:$I$386)} -> 26405 | J6: {=SUMPRODUCT(('📋 Lançamentos'!$B$3:$B$386="Setembro")*('📋 Lançamentos'!$E$3:$E$386="Receita")*('📋 Lançamentos'!$C$3:$C$386="Bebidas"),'📋 Lançamentos'!$I$3:$I$386)} -> 25961 | K6: {=SUMPRODUCT(('📋 Lançamentos'!$B$3:$B$386="Outubro")*('📋 Lançamentos'!$E$3:$E$386="Receita")*('📋 Lançamentos'!$C$3:$C$386="Bebidas"),'📋 Lançamentos'!$I$3:$I$386)} -> 28230 | L6: {=SUMPRODUCT(('📋 Lançamentos'!$B$3:$B$386="Novembro")*('📋 Lançamentos'!$E$3:$E$386="Receita")*('📋 Lançamentos'!$C$3:$C$386="Bebidas"),'📋 Lançamentos'!$I$3:$I$386)} -> 28393 | M6: {=SUMPRODUCT(('📋 Lançamentos'!$B$3:$B$386="Dezembro")*('📋 Lançamentos'!$E$3:$E$386="Receita")*('📋 Lançamentos'!$C$3:$C$386="Bebidas"),'📋 Lançamentos'!$I$3:$I$386)} -> 32801 | N6: =SUM(B6:M6) -> 309806
A7: Delivery | B7: {=SUMPRODUCT(('📋 Lançamentos'!$B$3:$B$386="Janeiro")*('📋 Lançamentos'!$E$3:$E$386="Receita")*('📋 Lançamentos'!$C$3:$C$386="Delivery"),'📋 Lançamentos'!$I$3:$I$386)} -> 27253 | C7: {=SUMPRODUCT(('📋 Lançamentos'!$B$3:$B$386="Fevereiro")*('📋 Lançamentos'!$E$3:$E$386="Receita")*('📋 Lançamentos'!$C$3:$C$386="Delivery"),'📋 Lançamentos'!$I$3:$I$386)} -> 27196 | D7: {=SUMPRODUCT(('📋 Lançamentos'!$B$3:$B$386="Março")*('📋 Lançamentos'!$E$3:$E$386="Receita")*('📋 Lançamentos'!$C$3:$C$386="Delivery"),'📋 Lançamentos'!$I$3:$I$386)} -> 31493 | E7: {=SUMPRODUCT(('📋 Lançamentos'!$B$3:$B$386="Abril")*('📋 Lançamentos'!$E$3:$E$386="Receita")*('📋 Lançamentos'!$C$3:$C$386="Delivery"),'📋 Lançamentos'!$I$3:$I$386)} -> 35208 | F7: {=SUMPRODUCT(('📋 Lançamentos'!$B$3:$B$386="Maio")*('📋 Lançamentos'!$E$3:$E$386="Receita")*('📋 Lançamentos'!$C$3:$C$386="Delivery"),'📋 Lançamentos'!$I$3:$I$386)} -> 35953 | G7: {=SUMPRODUCT(('📋 Lançamentos'!$B$3:$B$386="Junho")*('📋 Lançamentos'!$E$3:$E$386="Receita")*('📋 Lançamentos'!$C$3:$C$386="Delivery"),'📋 Lançamentos'!$I$3:$I$386)} -> 39246 | H7: {=SUMPRODUCT(('📋 Lançamentos'!$B$3:$B$386="Julho")*('📋 Lançamentos'!$E$3:$E$386="Receita")*('📋 Lançamentos'!$C$3:$C$386="Delivery"),'📋 Lançamentos'!$I$3:$I$386)} -> 40116 | I7: {=SUMPRODUCT(('📋 Lançamentos'!$B$3:$B$386="Agosto")*('📋 Lançamentos'!$E$3:$E$386="Receita")*('📋 Lançamentos'!$C$3:$C$386="Delivery"),'📋 Lançamentos'!$I$3:$I$386)} -> 34473 | J7: {=SUMPRODUCT(('📋 Lançamentos'!$B$3:$B$386="Setembro")*('📋 Lançamentos'!$E$3:$E$386="Receita")*('📋 Lançamentos'!$C$3:$C$386="Delivery"),'📋 Lançamentos'!$I$3:$I$386)} -> 34243 | K7: {=SUMPRODUCT(('📋 Lançamentos'!$B$3:$B$386="Outubro")*('📋 Lançamentos'!$E$3:$E$386="Receita")*('📋 Lançamentos'!$C$3:$C$386="Delivery"),'📋 Lançamentos'!$I$3:$I$386)} -> 36416 | L7: {=SUMPRODUCT(('📋 Lançamentos'!$B$3:$B$386="Novembro")*('📋 Lançamentos'!$E$3:$E$386="Receita")*('📋 Lançamentos'!$C$3:$C$386="Delivery"),'📋 Lançamentos'!$I$3:$I$386)} -> 39816 | M7: {=SUMPRODUCT(('📋 Lançamentos'!$B$3:$B$386="Dezembro")*('📋 Lançamentos'!$E$3:$E$386="Receita")*('📋 Lançamentos'!$C$3:$C$386="Delivery"),'📋 Lançamentos'!$I$3:$I$386)} -> 47960 | N7: =SUM(B7:M7) -> 429373
A8: Eventos | B8: {=SUMPRODUCT(('📋 Lançamentos'!$B$3:$B$386="Janeiro")*('📋 Lançamentos'!$E$3:$E$386="Receita")*('📋 Lançamentos'!$C$3:$C$386="Eventos"),'📋 Lançamentos'!$I$3:$I$386)} -> 8650 | C8: {=SUMPRODUCT(('📋 Lançamentos'!$B$3:$B$386="Fevereiro")*('📋 Lançamentos'!$E$3:$E$386="Receita")*('📋 Lançamentos'!$C$3:$C$386="Eventos"),'📋 Lançamentos'!$I$3:$I$386)} -> 8650 | D8: {=SUMPRODUCT(('📋 Lançamentos'!$B$3:$B$386="Março")*('📋 Lançamentos'!$E$3:$E$386="Receita")*('📋 Lançamentos'!$C$3:$C$386="Eventos"),'📋 Lançamentos'!$I$3:$I$386)} -> 11100 | E8: {=SUMPRODUCT(('📋 Lançamentos'!$B$3:$B$386="Abril")*('📋 Lançamentos'!$E$3:$E$386="Receita")*('📋 Lançamentos'!$C$3:$C$386="Eventos"),'📋 Lançamentos'!$I$3:$I$386)} -> 11100 | F8: {=SUMPRODUCT(('📋 Lançamentos'!$B$3:$B$386="Maio")*('📋 Lançamentos'!$E$3:$E$386="Receita")*('📋 Lançamentos'!$C$3:$C$386="Eventos"),'📋 Lançamentos'!$I$3:$I$386)} -> 11100 | G8: {=SUMPRODUCT(('📋 Lançamentos'!$B$3:$B$386="Junho")*('📋 Lançamentos'!$E$3:$E$386="Receita")*('📋 Lançamentos'!$C$3:$C$386="Eventos"),'📋 Lançamentos'!$I$3:$I$386)} -> 11100 | H8: {=SUMPRODUCT(('📋 Lançamentos'!$B$3:$B$386="Julho")*('📋 Lançamentos'!$E$3:$E$386="Receita")*('📋 Lançamentos'!$C$3:$C$386="Eventos"),'📋 Lançamentos'!$I$3:$I$386)} -> 11100 | I8: {=SUMPRODUCT(('📋 Lançamentos'!$B$3:$B$386="Agosto")*('📋 Lançamentos'!$E$3:$E$386="Receita")*('📋 Lançamentos'!$C$3:$C$386="Eventos"),'📋 Lançamentos'!$I$3:$I$386)} -> 11100 | J8: {=SUMPRODUCT(('📋 Lançamentos'!$B$3:$B$386="Setembro")*('📋 Lançamentos'!$E$3:$E$386="Receita")*('📋 Lançamentos'!$C$3:$C$386="Eventos"),'📋 Lançamentos'!$I$3:$I$386)} -> 11750 | K8: {=SUMPRODUCT(('📋 Lançamentos'!$B$3:$B$386="Outubro")*('📋 Lançamentos'!$E$3:$E$386="Receita")*('📋 Lançamentos'!$C$3:$C$386="Eventos"),'📋 Lançamentos'!$I$3:$I$386)} -> 13550 | L8: {=SUMPRODUCT(('📋 Lançamentos'!$B$3:$B$386="Novembro")*('📋 Lançamentos'!$E$3:$E$386="Receita")*('📋 Lançamentos'!$C$3:$C$386="Eventos"),'📋 Lançamentos'!$I$3:$I$386)} -> 13550 | M8: {=SUMPRODUCT(('📋 Lançamentos'!$B$3:$B$386="Dezembro")*('📋 Lançamentos'!$E$3:$E$386="Receita")*('📋 Lançamentos'!$C$3:$C$386="Eventos"),'📋 Lançamentos'!$I$3:$I$386)} -> 14200 | N8: =SUM(B8:M8) -> 136950
A9: RECEITA BRUTA TOTAL | B9: =SUM(B5:B8) -> 82926 | C9: =SUM(C5:C8) -> 84534 | D9: =SUM(D5:D8) -> 97722 | E9: =SUM(E5:E8) -> 108388 | F9: =SUM(F5:F8) -> 110071 | G9: =SUM(G5:G8) -> 118631 | H9: =SUM(H5:H8) -> 120257 | I9: =SUM(I5:I8) -> 111396 | ... M9: =SUM(M5:M8) -> 144199 | N9: =SUM(B9:M9) -> 1323449
A10: ▶ DEDUÇÕES E IMPOSTOS
A11: Impostos sobre Receita (ISS/PIS/COFINS) | B11: {=SUMPRODUCT(('📋 Lançamentos'!$B$3:$B$10000="Janeiro")*('📋 Lançamentos'!$E$3:$E$10000="Despesa")*('📋 Lançamentos'!$C$3:$C$10000="Taxas/Impostos"),'📋 Lançamentos'!$I$3:$I$10000)} -> 8631.26 | C11: {=SUMPRODUCT(('📋 Lançamentos'!$B$3:$B$10000="Fevereiro")*('📋 Lançamentos'!$E$3:$E$10000="Despesa")*('📋 Lançamentos'!$C$3:$C$10000="Taxas/Impostos"),'📋 Lançamentos'!$I$3:$I$10000)} -> 8845.91 | D11: {=SUMPRODUCT(('📋 Lançamentos'!$B$3:$B$10000="Março")*('📋 Lançamentos'!$E$3:$E$10000="Despesa")*('📋 Lançamentos'!$C$3:$C$10000="Taxas/Impostos"),'📋 Lançamentos'!$I$3:$I$10000)} -> 9923.77 | E11: {=SUMPRODUCT(('📋 Lançamentos'!$B$3:$B$10000="Abril")*('📋 Lançamentos'!$E$3:$E$10000="Despesa")*('📋 Lançamentos'!$C$3:$C$10000="Taxas/Impostos"),'📋 Lançamentos'!$I$3:$I$10000)} -> 10759.13 | F11: {=SUMPRODUCT(('📋 Lançamentos'!$B$3:$B$10000="Maio")*('📋 Lançamentos'!$E$3:$E$10000="Despesa")*('📋 Lançamentos'!$C$3:$C$10000="Taxas/Impostos"),'📋 Lançamentos'!$I$3:$I$10000)} -> 11241.16 | G11: {=SUMPRODUCT(('📋 Lançamentos'!$B$3:$B$10000="Junho")*('📋 Lançamentos'!$E$3:$E$10000="Despesa")*('📋 Lançamentos'!$C$3:$C$10000="Taxas/Impostos"),'📋 Lançamentos'!$I$3:$I$10000)} -> 11865.84 | H11: {=SUMPRODUCT(('📋 Lançamentos'!$B$3:$B$10000="Julho")*('📋 Lançamentos'!$E$3:$E$10000="Despesa")*('📋 Lançamentos'!$C$3:$C$10000="Taxas/Impostos"),'📋 Lançamentos'!$I$3:$I$10000)} -> 12958.37 | I11: {=SUMPRODUCT(('📋 Lançamentos'!$B$3:$B$10000="Agosto")*('📋 Lançamentos'!$E$3:$E$10000="Despesa")*('📋 Lançamentos'!$C$3:$C$10000="Taxas/Impostos"),'📋 Lançamentos'!$I$3:$I$10000)} -> 12059.26 | J11: {=SUMPRODUCT(('📋 Lançamentos'!$B$3:$B$10000="Setembro")*('📋 Lançamentos'!$E$3:$E$10000="Despesa")*('📋 Lançamentos'!$C$3:$C$10000="Taxas/Impostos"),'📋 Lançamentos'!$I$3:$I$10000)} -> 11177.17 | K11: {=SUMPRODUCT(('📋 Lançamentos'!$B$3:$B$10000="Outubro")*('📋 Lançamentos'!$E$3:$E$10000="Despesa")*('📋 Lançamentos'!$C$3:$C$10000="Taxas/Impostos"),'📋 Lançamentos'!$I$3:$I$10000)} -> 12257.16 | L11: {=SUMPRODUCT(('📋 Lançamentos'!$B$3:$B$10000="Novembro")*('📋 Lançamentos'!$E$3:$E$10000="Despesa")*('📋 Lançamentos'!$C$3:$C$10000="Taxas/Impostos"),'📋 Lançamentos'!$I$3:$I$10000)} -> 13012.7 | M11: {=SUMPRODUCT(('📋 Lançamentos'!$B$3:$B$10000="Dezembro")*('📋 Lançamentos'!$E$3:$E$10000="Despesa")*('📋 Lançamentos'!$C$3:$C$10000="Taxas/Impostos"),'📋 Lançamentos'!$I$3:$I$10000)} -> 14967.87 | N11: =SUM(B11:M11) -> 137699.6
A12: TOTAL DEDUÇÕES | B12: =-B11 -> -8631.26 | C12: =-C11 -> -8845.91 | D12: =-D11 -> -9923.77 | E12: =-E11 -> -10759.13 | F12: =-F11 -> -11241.16 | G12: =-G11 -> -11865.84 | H12: =-H11 -> -12958.37 | I12: =-I11 -> -12059.26 | ... M12: =-M11 -> -14967.87 | N12: =SUM(B12:M12) -> -137699.6
A13: RECEITA LÍQUIDA | B13: =B9+B12 -> 74294.74 | C13: =C9+C12 -> 75688.09 | D13: =D9+D12 -> 87798.23 | E13: =E9+E12 -> 97628.87 | F13: =F9+F12 -> 98829.84 | G13: =G9+G12 -> 106765.16 | H13: =H9+H12 -> 107298.63 | I13: =I9+I12 -> 99336.74 | ... M13: =M9+M12 -> 129231.13 | N13: =SUM(B13:M13) -> 1185749.4
A15: ▶ CUSTOS OPERACIONAIS
A16: Embalagens Delivery | B16: {=SUMPRODUCT(('📋 Lançamentos'!$B$3:$B$10000="Janeiro")*('📋 Lançamentos'!$E$3:$E$10000="Despesa")*('📋 Lançamentos'!$D$3:$D$10000="Embalagens Delivery"),'📋 Lançamentos'!$I$3:$I$10000)} -> 1400.93 | C16: {=SUMPRODUCT(('📋 Lançamentos'!$B$3:$B$10000="Fevereiro")*('📋 Lançamentos'!$E$3:$E$10000="Despesa")*('📋 Lançamentos'!$D$3:$D$10000="Embalagens Delivery"),'📋 Lançamentos'!$I$3:$I$10000)} -> 1464.09 | D16: {=SUMPRODUCT(('📋 Lançamentos'!$B$3:$B$10000="Março")*('📋 Lançamentos'!$E$3:$E$10000="Despesa")*('📋 Lançamentos'!$D$3:$D$10000="Embalagens Delivery"),'📋 Lançamentos'!$I$3:$I$10000)} -> 1589.02 | E16: {=SUMPRODUCT(('📋 Lançamentos'!$B$3:$B$10000="Abril")*('📋 Lançamentos'!$E$3:$E$10000="Despesa")*('📋 Lançamentos'!$D$3:$D$10000="Embalagens Delivery"),'📋 Lançamentos'!$I$3:$I$10000)} -> 1783.1 | F16: {=SUMPRODUCT(('📋 Lançamentos'!$B$3:$B$10000="Maio")*('📋 Lançamentos'!$E$3:$E$10000="Despesa")*('📋 Lançamentos'!$D$3:$D$10000="Embalagens Delivery"),'📋 Lançamentos'!$I$3:$I$10000)} -> 1946.08 | G16: {=SUMPRODUCT(('📋 Lançamentos'!$B$3:$B$10000="Junho")*('📋 Lançamentos'!$E$3:$E$10000="Despesa")*('📋 Lançamentos'!$D$3:$D$10000="Embalagens Delivery"),'📋 Lançamentos'!$I$3:$I$10000)} -> 2017.85 | H16: {=SUMPRODUCT(('📋 Lançamentos'!$B$3:$B$10000="Julho")*('📋 Lançamentos'!$E$3:$E$10000="Despesa")*('📋 Lançamentos'!$D$3:$D$10000="Embalagens Delivery"),'📋 Lançamentos'!$I$3:$I$10000)} -> 2074.06 | I16: {=SUMPRODUCT(('📋 Lançamentos'!$B$3:$B$10000="Agosto")*('📋 Lançamentos'!$E$3:$E$10000="Despesa")*('📋 Lançamentos'!$D$3:$D$10000="Embalagens Delivery"),'📋 Lançamentos'!$I$3:$I$10000)} -> 1985.63 | J16: {=SUMPRODUCT(('📋 Lançamentos'!$B$3:$B$10000="Setembro")*('📋 Lançamentos'!$E$3:$E$10000="Despesa")*('📋 Lançamentos'!$D$3:$D$10000="Embalagens Delivery"),'📋 Lançamentos'!$I$3:$I$10000)} -> 1908.46 | K16: {=SUMPRODUCT(('📋 Lançamentos'!$B$3:$B$10000="Outubro")*('📋 Lançamentos'!$E$3:$E$10000="Despesa")*('📋 Lançamentos'!$D$3:$D$10000="Embalagens Delivery"),'📋 Lançamentos'!$I$3:$I$10000)} -> 1948.85 | L16: {=SUMPRODUCT(('📋 Lançamentos'!$B$3:$B$10000="Novembro")*('📋 Lançamentos'!$E$3:$E$10000="Despesa")*('📋 Lançamentos'!$D$3:$D$10000="Embalagens Delivery"),'📋 Lançamentos'!$I$3:$I$10000)} -> 2089.27 | M16: {=SUMPRODUCT(('📋 Lançamentos'!$B$3:$B$10000="Dezembro")*('📋 Lançamentos'!$E$3:$E$10000="Despesa")*('📋 Lançamentos'!$D$3:$D$10000="Embalagens Delivery"),'📋 Lançamentos'!$I$3:$I$10000)} -> 2512.29 | N16: =SUM(B16:M16) -> 22719.63
A17: Produtos de Limpeza | B17: {=SUMPRODUCT(('📋 Lançamentos'!$B$3:$B$10000="Janeiro")*('📋 Lançamentos'!$E$3:$E$10000="Despesa")*('📋 Lançamentos'!$D$3:$D$10000="Produtos de Limpeza"),'📋 Lançamentos'!$I$3:$I$10000)} -> 499.79 | C17: {=SUMPRODUCT(('📋 Lançamentos'!$B$3:$B$10000="Fevereiro")*('📋 Lançamentos'!$E$3:$E$10000="Despesa")*('📋 Lançamentos'!$D$3:$D$10000="Produtos de Limpeza"),'📋 Lançamentos'!$I$3:$I$10000)} -> 503.76 | D17: {=SUMPRODUCT(('📋 Lançamentos'!$B$3:$B$10000="Março")*('📋 Lançamentos'!$E$3:$E$10000="Despesa")*('📋 Lançamentos'!$D$3:$D$10000="Produtos de Limpeza"),'📋 Lançamentos'!$I$3:$I$10000)} -> 568.85 | E17: {=SUMPRODUCT(('📋 Lançamentos'!$B$3:$B$10000="Abril")*('📋 Lançamentos'!$E$3:$E$10000="Despesa")*('📋 Lançamentos'!$D$3:$D$10000="Produtos de Limpeza"),'📋 Lançamentos'!$I$3:$I$10000)} -> 623.61 | F17: {=SUMPRODUCT(('📋 Lançamentos'!$B$3:$B$10000="Maio")*('📋 Lançamentos'!$E$3:$E$10000="Despesa")*('📋 Lançamentos'!$D$3:$D$10000="Produtos de Limpeza"),'📋 Lançamentos'!$I$3:$I$10000)} -> 637.02 | G17: {=SUMPRODUCT(('📋 Lançamentos'!$B$3:$B$10000="Junho")*('📋 Lançamentos'!$E$3:$E$10000="Despesa")*('📋 Lançamentos'!$D$3:$D$10000="Produtos de Limpeza"),'📋 Lançamentos'!$I$3:$I$10000)} -> 682.67 | H17: {=SUMPRODUCT(('📋 Lançamentos'!$B$3:$B$10000="Julho")*('📋 Lançamentos'!$E$3:$E$10000="Despesa")*('📋 Lançamentos'!$D$3:$D$10000="Produtos de Limpeza"),'📋 Lançamentos'!$I$3:$I$10000)} -> 724.69 | I17: {=SUMPRODUCT(('📋 Lançamentos'!$B$3:$B$10000="Agosto")*('📋 Lançamentos'!$E$3:$E$10000="Despesa")*('📋 Lançamentos'!$D$3:$D$10000="Produtos de Limpeza"),'📋 Lançamentos'!$I$3:$I$10000)} -> 656.89 | J17: {=SUMPRODUCT(('📋 Lançamentos'!$B$3:$B$10000="Setembro")*('📋 Lançamentos'!$E$3:$E$10000="Despesa")*('📋 Lançamentos'!$D$3:$D$10000="Produtos de Limpeza"),'📋 Lançamentos'!$I$3:$I$10000)} -> 657.56 | K17: {=SUMPRODUCT(('📋 Lançamentos'!$B$3:$B$10000="Outubro")*('📋 Lançamentos'!$E$3:$E$10000="Despesa")*('📋 Lançamentos'!$D$3:$D$10000="Produtos de Limpeza"),'📋 Lançamentos'!$I$3:$I$10000)} -> 714.92 | L17: {=SUMPRODUCT(('📋 Lançamentos'!$B$3:$B$10000="Novembro")*('📋 Lançamentos'!$E$3:$E$10000="Despesa")*('📋 Lançamentos'!$D$3:$D$10000="Produtos de Limpeza"),'📋 Lançamentos'!$I$3:$I$10000)} -> 755.48 | M17: {=SUMPRODUCT(('📋 Lançamentos'!$B$3:$B$10000="Dezembro")*('📋 Lançamentos'!$E$3:$E$10000="Despesa")*('📋 Lançamentos'!$D$3:$D$10000="Produtos de Limpeza"),'📋 Lançamentos'!$I$3:$I$10000)} -> 867.6 | N17: =SUM(B17:M17) -> 7892.84
A18: Uniformes | B18: {=SUMPRODUCT(('📋 Lançamentos'!$B$3:$B$10000="Janeiro")*('📋 Lançamentos'!$E$3:$E$10000="Despesa")*('📋 Lançamentos'!$D$3:$D$10000="Uniformes"),'📋 Lançamentos'!$I$3:$I$10000)} -> 314.8 | C18: {=SUMPRODUCT(('📋 Lançamentos'!$B$3:$B$10000="Fevereiro")*('📋 Lançamentos'!$E$3:$E$10000="Despesa")*('📋 Lançamentos'!$D$3:$D$10000="Uniformes"),'📋 Lançamentos'!$I$3:$I$10000)} -> 312.46 | D18: {=SUMPRODUCT(('📋 Lançamentos'!$B$3:$B$10000="Março")*('📋 Lançamentos'!$E$3:$E$10000="Despesa")*('📋 Lançamentos'!$D$3:$D$10000="Uniformes"),'📋 Lançamentos'!$I$3:$I$10000)} -> 334.65 | E18: {=SUMPRODUCT(('📋 Lançamentos'!$B$3:$B$10000="Abril")*('📋 Lançamentos'!$E$3:$E$10000="Despesa")*('📋 Lançamentos'!$D$3:$D$10000="Uniformes"),'📋 Lançamentos'!$I$3:$I$10000)} -> 391.83 | F18: {=SUMPRODUCT(('📋 Lançamentos'!$B$3:$B$10000="Maio")*('📋 Lançamentos'!$E$3:$E$10000="Despesa")*('📋 Lançamentos'!$D$3:$D$10000="Uniformes"),'📋 Lançamentos'!$I$3:$I$10000)} -> 407.32 | G18: {=SUMPRODUCT(('📋 Lançamentos'!$B$3:$B$10000="Junho")*('📋 Lançamentos'!$E$3:$E$10000="Despesa")*('📋 Lançamentos'!$D$3:$D$10000="Uniformes"),'📋 Lançamentos'!$I$3:$I$10000)} -> 407.1 | H18: {=SUMPRODUCT(('📋 Lançamentos'!$B$3:$B$10000="Julho")*('📋 Lançamentos'!$E$3:$E$10000="Despesa")*('📋 Lançamentos'!$D$3:$D$10000="Uniformes"),'📋 Lançamentos'!$I$3:$I$10000)} -> 437.85 | I18: {=SUMPRODUCT(('📋 Lançamentos'!$B$3:$B$10000="Agosto")*('📋 Lançamentos'!$E$3:$E$10000="Despesa")*('📋 Lançamentos'!$D$3:$D$10000="Uniformes"),'📋 Lançamentos'!$I$3:$I$10000)} -> 405.31 | J18: {=SUMPRODUCT(('📋 Lançamentos'!$B$3:$B$10000="Setembro")*('📋 Lançamentos'!$E$3:$E$10000="Despesa")*('📋 Lançamentos'!$D$3:$D$10000="Uniformes"),'📋 Lançamentos'!$I$3:$I$10000)} -> 377.78 | K18: {=SUMPRODUCT(('📋 Lançamentos'!$B$3:$B$10000="Outubro")*('📋 Lançamentos'!$E$3:$E$10000="Despesa")*('📋 Lançamentos'!$D$3:$D$10000="Uniformes"),'📋 Lançamentos'!$I$3:$I$10000)} -> 435.02 | L18: {=SUMPRODUCT(('📋 Lançamentos'!$B$3:$B$10000="Novembro")*('📋 Lançamentos'!$E$3:$E$10000="Despesa")*('📋 Lançamentos'!$D$3:$D$10000="Uniformes"),'📋 Lançamentos'!$I$3:$I$10000)} -> 437.59 | M18: {=SUMPRODUCT(('📋 Lançamentos'!$B$3:$B$10000="Dezembro")*('📋 Lançamentos'!$E$3:$E$10000="Despesa")*('📋 Lançamentos'!$D$3:$D$10000="Uniformes"),'📋 Lançamentos'!$I$3:$I$10000)} -> 530.52 | N18: =SUM(B18:M18) -> 4792.23
A19: Manutenção Equip. | B19: {=SUMPRODUCT(('📋 Lançamentos'!$B$3:$B$10000="Janeiro")*('📋 Lançamentos'!$E$3:$E$10000="Despesa")*('📋 Lançamentos'!$D$3:$D$10000="Manutenção Equip."),'📋 Lançamentos'!$I$3:$I$10000)} -> 740.3 | C19: {=SUMPRODUCT(('📋 Lançamentos'!$B$3:$B$10000="Fevereiro")*('📋 Lançamentos'!$E$3:$E$10000="Despesa")*('📋 Lançamentos'!$D$3:$D$10000="Manutenção Equip."),'📋 Lançamentos'!$I$3:$I$10000)} -> 802.65 | D19: {=SUMPRODUCT(('📋 Lançamentos'!$B$3:$B$10000="Março")*('📋 Lançamentos'!$E$3:$E$10000="Despesa")*('📋 Lançamentos'!$D$3:$D$10000="Manutenção Equip."),'📋 Lançamentos'!$I$3:$I$10000)} -> 865.71 | E19: {=SUMPRODUCT(('📋 Lançamentos'!$B$3:$B$10000="Abril")*('📋 Lançamentos'!$E$3:$E$10000="Despesa")*('📋 Lançamentos'!$D$3:$D$10000="Manutenção Equip."),'📋 Lançamentos'!$I$3:$I$10000)} -> 962.54 | F19: {=SUMPRODUCT(('📋 Lançamentos'!$B$3:$B$10000="Maio")*('📋 Lançamentos'!$E$3:$E$10000="Despesa")*('📋 Lançamentos'!$D$3:$D$10000="Manutenção Equip."),'📋 Lançamentos'!$I$3:$I$10000)} -> 970.46 | G19: {=SUMPRODUCT(('📋 Lançamentos'!$B$3:$B$10000="Junho")*('📋 Lançamentos'!$E$3:$E$10000="Despesa")*('📋 Lançamentos'!$D$3:$D$10000="Manutenção Equip."),'📋 Lançamentos'!$I$3:$I$10000)} -> 1086.1 | H19: {=SUMPRODUCT(('📋 Lançamentos'!$B$3:$B$10000="Julho")*('📋 Lançamentos'!$E$3:$E$10000="Despesa")*('📋 Lançamentos'!$D$3:$D$10000="Manutenção Equip."),'📋 Lançamentos'!$I$3:$I$10000)} -> 1069.92 | I19: {=SUMPRODUCT(('📋 Lançamentos'!$B$3:$B$10000="Agosto")*('📋 Lançamentos'!$E$3:$E$10000="Despesa")*('📋 Lançamentos'!$D$3:$D$10000="Manutenção Equip."),'📋 Lançamentos'!$I$3:$I$10000)} -> 1007.39 | J19: {=SUMPRODUCT(('📋 Lançamentos'!$B$3:$B$10000="Setembro")*('📋 Lançamentos'!$E$3:$E$10000="Despesa")*('📋 Lançamentos'!$D$3:$D$10000="Manutenção Equip."),'📋 Lançamentos'!$I$3:$I$10000)} -> 993.73 | K19: {=SUMPRODUCT(('📋 Lançamentos'!$B$3:$B$10000="Outubro")*('📋 Lançamentos'!$E$3:$E$10000="Despesa")*('📋 Lançamentos'!$D$3:$D$10000="Manutenção Equip."),'📋 Lançamentos'!$I$3:$I$10000)} -> 1037.75 | L19: {=SUMPRODUCT(('📋 Lançamentos'!$B$3:$B$10000="Novembro")*('📋 Lançamentos'!$E$3:$E$10000="Despesa")*('📋 Lançamentos'!$D$3:$D$10000="Manutenção Equip."),'📋 Lançamentos'!$I$3:$I$10000)} -> 1079.77 | M19: {=SUMPRODUCT(('📋 Lançamentos'!$B$3:$B$10000="Dezembro")*('📋 Lançamentos'!$E$3:$E$10000="Despesa")*('📋 Lançamentos'!$D$3:$D$10000="Manutenção Equip."),'📋 Lançamentos'!$I$3:$I$10000)} -> 1310.79 | N19: =SUM(B19:M19) -> 11927.11
A20: Pessoal | B20: {=SUMPRODUCT(('📋 Lançamentos'!$B$3:$B$10000="Janeiro")*('📋 Lançamentos'!$E$3:$E$10000="Despesa")*('📋 Lançamentos'!$C$3:$C$10000="Pessoal"),'📋 Lançamentos'!$I$3:$I$10000)} -> 26743.93 | C20: {=SUMPRODUCT(('📋 Lançamentos'!$B$3:$B$10000="Fevereiro")*('📋 Lançamentos'!$E$3:$E$10000="Despesa")*('📋 Lançamentos'!$C$3:$C$10000="Pessoal"),'📋 Lançamentos'!$I$3:$I$10000)} -> 28000.43 | D20: {=SUMPRODUCT(('📋 Lançamentos'!$B$3:$B$10000="Março")*('📋 Lançamentos'!$E$3:$E$10000="Despesa")*('📋 Lançamentos'!$C$3:$C$10000="Pessoal"),'📋 Lançamentos'!$I$3:$I$10000)} -> 30356.93 | E20: {=SUMPRODUCT(('📋 Lançamentos'!$B$3:$B$10000="Abril")*('📋 Lançamentos'!$E$3:$E$10000="Despesa")*('📋 Lançamentos'!$C$3:$C$10000="Pessoal"),'📋 Lançamentos'!$I$3:$I$10000)} -> 33870.29 | F20: {=SUMPRODUCT(('📋 Lançamentos'!$B$3:$B$10000="Maio")*('📋 Lançamentos'!$E$3:$E$10000="Despesa")*('📋 Lançamentos'!$C$3:$C$10000="Pessoal"),'📋 Lançamentos'!$I$3:$I$10000)} -> 35741.19 | G20: {=SUMPRODUCT(('📋 Lançamentos'!$B$3:$B$10000="Junho")*('📋 Lançamentos'!$E$3:$E$10000="Despesa")*('📋 Lançamentos'!$C$3:$C$10000="Pessoal"),'📋 Lançamentos'!$I$3:$I$10000)} -> 37322.37 | H20: {=SUMPRODUCT(('📋 Lançamentos'!$B$3:$B$10000="Julho")*('📋 Lançamentos'!$E$3:$E$10000="Despesa")*('📋 Lançamentos'!$C$3:$C$10000="Pessoal"),'📋 Lançamentos'!$I$3:$I$10000)} -> 39494.92 | I20: {=SUMPRODUCT(('📋 Lançamentos'!$B$3:$B$10000="Agosto")*('📋 Lançamentos'!$E$3:$E$10000="Despesa")*('📋 Lançamentos'!$C$3:$C$10000="Pessoal"),'📋 Lançamentos'!$I$3:$I$10000)} -> 36411.5 | J20: {=SUMPRODUCT(('📋 Lançamentos'!$B$3:$B$10000="Setembro")*('📋 Lançamentos'!$E$3:$E$10000="Despesa")*('📋 Lançamentos'!$C$3:$C$10000="Pessoal"),'📋 Lançamentos'!$I$3:$I$10000)} -> 34161 | K20: {=SUMPRODUCT(('📋 Lançamentos'!$B$3:$B$10000="Outubro")*('📋 Lançamentos'!$E$3:$E$10000="Despesa")*('📋 Lançamentos'!$C$3:$C$10000="Pessoal"),'📋 Lançamentos'!$I$3:$I$10000)} -> 38593.92 | L20: {=SUMPRODUCT(('📋 Lançamentos'!$B$3:$B$10000="Novembro")*('📋 Lançamentos'!$E$3:$E$10000="Despesa")*('📋 Lançamentos'!$C$3:$C$10000="Pessoal"),'📋 Lançamentos'!$I$3:$I$10000)} -> 39492.51 | M20: {=SUMPRODUCT(('📋 Lançamentos'!$B$3:$B$10000="Dezembro")*('📋 Lançamentos'!$E$3:$E$10000="Despesa")*('📋 Lançamentos'!$C$3:$C$10000="Pessoal"),'📋 Lançamentos'!$I$3:$I$10000)} -> 44715.44 | N20: =SUM(B20:M20) -> 424904.43
A21: TOTAL CUSTOS OPERACIONAIS | B21: =SUM(B16:B20) -> 29699.75 | C21: =SUM(C16:C20) -> 31083.39 | D21: =SUM(D16:D20) -> 33715.16 | E21: =SUM(E16:E20) -> 37631.37 | F21: =SUM(F16:F20) -> 39702.07 | G21: =SUM(G16:G20) -> 41516.09 | H21: =SUM(H16:H20) -> 43801.44 | I21: =SUM(I16:I20) -> 40466.72 | ... M21: =SUM(M16:M20) -> 49936.64 | N21: =SUM(B21:M21) -> 472236.24
A22: LUCRO BRUTO | B22: =B13-B21 -> 44594.99 | C22: =C13-C21 -> 44604.7 | D22: =D13-D21 -> 54083.07 | E22: =E13-E21 -> 59997.5 | F22: =F13-F21 -> 59127.77 | G22: =G13-G21 -> 65249.07 | H22: =H13-H21 -> 63497.19 | I22: =I13-I21 -> 58870.02 | ... M22: =M13-M21 -> 79294.49 | N22: =SUM(B22:M22) -> 713513.16
A24: ▶ DESPESAS ADMINISTRATIVAS, MARKETING E CMV
A25: Infraestrutura (Aluguel/Energia) | B25: {=SUMPRODUCT(('📋 Lançamentos'!$B$3:$B$386="Janeiro")*('📋 Lançamentos'!$E$3:$E$386="Despesa")*('📋 Lançamentos'!$C$3:$C$386="Infraestrutura"),'📋 Lançamentos'!$I$3:$I$386)} -> 10975.48 | C25: {=SUMPRODUCT(('📋 Lançamentos'!$B$3:$B$386="Fevereiro")*('📋 Lançamentos'!$E$3:$E$386="Despesa")*('📋 Lançamentos'!$C$3:$C$386="Infraestrutura"),'📋 Lançamentos'!$I$3:$I$386)} -> 11531.03 | D25: {=SUMPRODUCT(('📋 Lançamentos'!$B$3:$B$386="Março")*('📋 Lançamentos'!$E$3:$E$386="Despesa")*('📋 Lançamentos'!$C$3:$C$386="Infraestrutura"),'📋 Lançamentos'!$I$3:$I$386)} -> 12658.48 | E25: {=SUMPRODUCT(('📋 Lançamentos'!$B$3:$B$386="Abril")*('📋 Lançamentos'!$E$3:$E$386="Despesa")*('📋 Lançamentos'!$C$3:$C$386="Infraestrutura"),'📋 Lançamentos'!$I$3:$I$386)} -> 14007.75 | F25: {=SUMPRODUCT(('📋 Lançamentos'!$B$3:$B$386="Maio")*('📋 Lançamentos'!$E$3:$E$386="Despesa")*('📋 Lançamentos'!$C$3:$C$386="Infraestrutura"),'📋 Lançamentos'!$I$3:$I$386)} -> 14419 | G25: {=SUMPRODUCT(('📋 Lançamentos'!$B$3:$B$386="Junho")*('📋 Lançamentos'!$E$3:$E$386="Despesa")*('📋 Lançamentos'!$C$3:$C$386="Infraestrutura"),'📋 Lançamentos'!$I$3:$I$386)} -> 15111.11 | H25: {=SUMPRODUCT(('📋 Lançamentos'!$B$3:$B$386="Julho")*('📋 Lançamentos'!$E$3:$E$386="Despesa")*('📋 Lançamentos'!$C$3:$C$386="Infraestrutura"),'📋 Lançamentos'!$I$3:$I$386)} -> 16181.95 | I25: {=SUMPRODUCT(('📋 Lançamentos'!$B$3:$B$386="Agosto")*('📋 Lançamentos'!$E$3:$E$386="Despesa")*('📋 Lançamentos'!$C$3:$C$386="Infraestrutura"),'📋 Lançamentos'!$I$3:$I$386)} -> 14957.29 | J25: {=SUMPRODUCT(('📋 Lançamentos'!$B$3:$B$386="Setembro")*('📋 Lançamentos'!$E$3:$E$386="Despesa")*('📋 Lançamentos'!$C$3:$C$386="Infraestrutura"),'📋 Lançamentos'!$I$3:$I$386)} -> 13954.68 | K25: {=SUMPRODUCT(('📋 Lançamentos'!$B$3:$B$386="Outubro")*('📋 Lançamentos'!$E$3:$E$386="Despesa")*('📋 Lançamentos'!$C$3:$C$386="Infraestrutura"),'📋 Lançamentos'!$I$3:$I$386)} -> 15652.24 | L25: {=SUMPRODUCT(('📋 Lançamentos'!$B$3:$B$386="Novembro")*('📋 Lançamentos'!$E$3:$E$386="Despesa")*('📋 Lançamentos'!$C$3:$C$386="Infraestrutura"),'📋 Lançamentos'!$I$3:$I$386)} -> 16228.22 | M25: {=SUMPRODUCT(('📋 Lançamentos'!$B$3:$B$386="Dezembro")*('📋 Lançamentos'!$E$3:$E$386="Despesa")*('📋 Lançamentos'!$C$3:$C$386="Infraestrutura"),'📋 Lançamentos'!$I$3:$I$386)} -> 18350.53 | N25: =SUM(B25:M25) -> 174027.76
A26: Marketing e Publicidade | B26: {=SUMPRODUCT(('📋 Lançamentos'!$B$3:$B$386="Janeiro")*('📋 Lançamentos'!$E$3:$E$386="Despesa")*('📋 Lançamentos'!$C$3:$C$386="Marketing"),'📋 Lançamentos'!$I$3:$I$386)} -> 1572.8 | C26: {=SUMPRODUCT(('📋 Lançamentos'!$B$3:$B$386="Fevereiro")*('📋 Lançamentos'!$E$3:$E$386="Despesa")*('📋 Lançamentos'!$C$3:$C$386="Marketing"),'📋 Lançamentos'!$I$3:$I$386)} -> 1671.66 | D26: {=SUMPRODUCT(('📋 Lançamentos'!$B$3:$B$386="Março")*('📋 Lançamentos'!$E$3:$E$386="Despesa")*('📋 Lançamentos'!$C$3:$C$386="Marketing"),'📋 Lançamentos'!$I$3:$I$386)} -> 1749.37 | E26: {=SUMPRODUCT(('📋 Lançamentos'!$B$3:$B$386="Abril")*('📋 Lançamentos'!$E$3:$E$386="Despesa")*('📋 Lançamentos'!$C$3:$C$386="Marketing"),'📋 Lançamentos'!$I$3:$I$386)} -> 2004.52 | F26: {=SUMPRODUCT(('📋 Lançamentos'!$B$3:$B$386="Maio")*('📋 Lançamentos'!$E$3:$E$386="Despesa")*('📋 Lançamentos'!$C$3:$C$386="Marketing"),'📋 Lançamentos'!$I$3:$I$386)} -> 2135.33 | G26: {=SUMPRODUCT(('📋 Lançamentos'!$B$3:$B$386="Junho")*('📋 Lançamentos'!$E$3:$E$386="Despesa")*('📋 Lançamentos'!$C$3:$C$386="Marketing"),'📋 Lançamentos'!$I$3:$I$386)} -> 2149.06 | H26: {=SUMPRODUCT(('📋 Lançamentos'!$B$3:$B$386="Julho")*('📋 Lançamentos'!$E$3:$E$386="Despesa")*('📋 Lançamentos'!$C$3:$C$386="Marketing"),'📋 Lançamentos'!$I$3:$I$386)} -> 2329.17 | I26: {=SUMPRODUCT(('📋 Lançamentos'!$B$3:$B$386="Agosto")*('📋 Lançamentos'!$E$3:$E$386="Despesa")*('📋 Lançamentos'!$C$3:$C$386="Marketing"),'📋 Lançamentos'!$I$3:$I$386)} -> 2095.47 | J26: {=SUMPRODUCT(('📋 Lançamentos'!$B$3:$B$386="Setembro")*('📋 Lançamentos'!$E$3:$E$386="Despesa")*('📋 Lançamentos'!$C$3:$C$386="Marketing"),'📋 Lançamentos'!$I$3:$I$386)} -> 2032.56 | K26: {=SUMPRODUCT(('📋 Lançamentos'!$B$3:$B$386="Outubro")*('📋 Lançamentos'!$E$3:$E$386="Despesa")*('📋 Lançamentos'!$C$3:$C$386="Marketing"),'📋 Lançamentos'!$I$3:$I$386)} -> 2251.3 | L26: {=SUMPRODUCT(('📋 Lançamentos'!$B$3:$B$386="Novembro")*('📋 Lançamentos'!$E$3:$E$386="Despesa")*('📋 Lançamentos'!$C$3:$C$386="Marketing"),'📋 Lançamentos'!$I$3:$I$386)} -> 2308.46 | M26: {=SUMPRODUCT(('📋 Lançamentos'!$B$3:$B$386="Dezembro")*('📋 Lançamentos'!$E$3:$E$386="Despesa")*('📋 Lançamentos'!$C$3:$C$386="Marketing"),'📋 Lançamentos'!$I$3:$I$386)} -> 2719.94 | N26: =SUM(B26:M26) -> 25019.64
A27: CMV | B27: {=SUMPRODUCT(('📋 Lançamentos'!$B$3:$B$386="Janeiro")*('📋 Lançamentos'!$E$3:$E$386="Despesa")*('📋 Lançamentos'!$C$3:$C$386="CMV"),'📋 Lançamentos'!$I$3:$I$386)} -> 30083.11 | C27: {=SUMPRODUCT(('📋 Lançamentos'!$B$3:$B$386="Fevereiro")*('📋 Lançamentos'!$E$3:$E$386="Despesa")*('📋 Lançamentos'!$C$3:$C$386="CMV"),'📋 Lançamentos'!$I$3:$I$386)} -> 30807.02 | D27: {=SUMPRODUCT(('📋 Lançamentos'!$B$3:$B$386="Março")*('📋 Lançamentos'!$E$3:$E$386="Despesa")*('📋 Lançamentos'!$C$3:$C$386="CMV"),'📋 Lançamentos'!$I$3:$I$386)} -> 33874.58 | E27: {=SUMPRODUCT(('📋 Lançamentos'!$B$3:$B$386="Abril")*('📋 Lançamentos'!$E$3:$E$386="Despesa")*('📋 Lançamentos'!$C$3:$C$386="CMV"),'📋 Lançamentos'!$I$3:$I$386)} -> 39105.42 | F27: {=SUMPRODUCT(('📋 Lançamentos'!$B$3:$B$386="Maio")*('📋 Lançamentos'!$E$3:$E$386="Despesa")*('📋 Lançamentos'!$C$3:$C$386="CMV"),'📋 Lançamentos'!$I$3:$I$386)} -> 39114.51 | G27: {=SUMPRODUCT(('📋 Lançamentos'!$B$3:$B$386="Junho")*('📋 Lançamentos'!$E$3:$E$386="Despesa")*('📋 Lançamentos'!$C$3:$C$386="CMV"),'📋 Lançamentos'!$I$3:$I$386)} -> 40843.69 | H27: {=SUMPRODUCT(('📋 Lançamentos'!$B$3:$B$386="Julho")*('📋 Lançamentos'!$E$3:$E$386="Despesa")*('📋 Lançamentos'!$C$3:$C$386="CMV"),'📋 Lançamentos'!$I$3:$I$386)} -> 43067.4 | I27: {=SUMPRODUCT(('📋 Lançamentos'!$B$3:$B$386="Agosto")*('📋 Lançamentos'!$E$3:$E$386="Despesa")*('📋 Lançamentos'!$C$3:$C$386="CMV"),'📋 Lançamentos'!$I$3:$I$386)} -> 40981.53 | J27: {=SUMPRODUCT(('📋 Lançamentos'!$B$3:$B$386="Setembro")*('📋 Lançamentos'!$E$3:$E$386="Despesa")*('📋 Lançamentos'!$C$3:$C$386="CMV"),'📋 Lançamentos'!$I$3:$I$386)} -> 39500.99 | K27: {=SUMPRODUCT(('📋 Lançamentos'!$B$3:$B$386="Outubro")*('📋 Lançamentos'!$E$3:$E$386="Despesa")*('📋 Lançamentos'!$C$3:$C$386="CMV"),'📋 Lançamentos'!$I$3:$I$386)} -> 41974.05 | L27: {=SUMPRODUCT(('📋 Lançamentos'!$B$3:$B$386="Novembro")*('📋 Lançamentos'!$E$3:$E$386="Despesa")*('📋 Lançamentos'!$C$3:$C$386="CMV"),'📋 Lançamentos'!$I$3:$I$386)} -> 45436.28 | M27: {=SUMPRODUCT(('📋 Lançamentos'!$B$3:$B$386="Dezembro")*('📋 Lançamentos'!$E$3:$E$386="Despesa")*('📋 Lançamentos'!$C$3:$C$386="CMV"),'📋 Lançamentos'!$I$3:$I$386)} -> 51432.72 | N27: =SUM(B27:M27) -> 476221.3
A28: TOTAL DESPESAS ADM. | B28: =SUM(B25:B27) -> 42631.39 | C28: =SUM(C25:C27) -> 44009.71 | D28: =SUM(D25:D27) -> 48282.43 | E28: =SUM(E25:E27) -> 55117.69 | F28: =SUM(F25:F27) -> 55668.84 | G28: =SUM(G25:G27) -> 58103.86 | H28: =SUM(H25:H27) -> 61578.52 | I28: =SUM(I25:I27) -> 58034.29 | ... N28: =SUM(N25:N27) -> 675268.7
A29: EBITDA (Resultado Operacional) | B29: =B22-B28 -> 1963.6 | C29: =C22-C28 -> 594.99 | D29: =D22-D28 -> 5800.64 | E29: =E22-E28 -> 4879.81 | F29: =F22-F28 -> 3458.93 | G29: =G22-G28 -> 7145.21 | H29: =H22-H28 -> 1918.67 | I29: =I22-I28 -> 835.73 | ... M29: =M22-M28 -> 6791.3 | N29: =SUM(B29:M29) -> 38244.46
A30: Margem EBITDA (%) | B30: =IFERROR(B29/B9,0) -> 0.023678943 | C30: =IFERROR(B29/B9,0) -> 0.023678943 | D30: =IFERROR(B29/B9,0) -> 0.023678943 | E30: =IFERROR(B29/B9,0) -> 0.023678943 | F30: =IFERROR(B29/B9,0) -> 0.023678943 | G30: =IFERROR(B29/B9,0) -> 0.023678943 | H30: =IFERROR(B29/B9,0) -> 0.023678943 | I30: =IFERROR(B29/B9,0) -> 0.023678943 | J30: =IFERROR(B29/B9,0) -> 0.023678943 | K30: =IFERROR(B29/B9,0) -> 0.023678943 | L30: =IFERROR(B29/B9,0) -> 0.023678943 | M30: =IFERROR(B29/B9,0) -> 0.023678943 | N30: =IFERROR(N29/N9,0) -> 0.02889757
A32: RESULTADO LÍQUIDO DO MÊS | B32: =B29 -> 1963.6 | C32: =C29 -> 594.99 | D32: =D29 -> 5800.64 | E32: =E29 -> 4879.81 | F32: =F29 -> 3458.93 | G32: =G29 -> 7145.21 | H32: =H29 -> 1918.67 | I32: =I29 -> 835.73 | ... N32: =N29 -> 38244.46

Sheet 🎯 Indicadores KPI
A1: 🎯 PAINEL DE INDICADORES — KPI FINANCEIRO 2024
B3: Jan | C3: Fev | D3: Mar | E3: Abr | F3: Mai | G3: Jun | H3: Jul | I3: Ago | J3: Set | K3: Out | L3: Nov | M3: Dez | N3: TOTAL
A4: 📈 Receita Bruta Total | B4: ='📊 DRE Mensal'!B9 -> 82926 | C4: ='📊 DRE Mensal'!C9 -> 84534 | D4: ='📊 DRE Mensal'!D9 -> 97722 | E4: ='📊 DRE Mensal'!E9 -> 108388 | F4: ='📊 DRE Mensal'!F9 -> 110071 | G4: ='📊 DRE Mensal'!G9 -> 118631 | H4: ='📊 DRE Mensal'!H9 -> 120257 | I4: ='📊 DRE Mensal'!I9 -> 111396 | ... M4: ='📊 DRE Mensal'!M9 -> 144199 | N4: =SUM(B4:M4) -> 1323449
A5: 💰 Receita Líquida | B5: ='📊 DRE Mensal'!B13 -> 74294.74 | C5: ='📊 DRE Mensal'!C13 -> 75688.09 | D5: ='📊 DRE Mensal'!D13 -> 87798.23 | E5: ='📊 DRE Mensal'!E13 -> 97628.87 | F5: ='📊 DRE Mensal'!F13 -> 98829.84 | G5: ='📊 DRE Mensal'!G13 -> 106765.16 | H5: ='📊 DRE Mensal'!H13 -> 107298.63 | I5: ='📊 DRE Mensal'!I13 -> 99336.74 | ... M5: ='📊 DRE Mensal'!M13 -> 129231.13 | N5: =SUM(B5:M5) -> 1185749.4
A6: 💸 Total Despesas | B6: ='📊 DRE Mensal'!B21+'📊 DRE Mensal'!B28 -> 72331.14 | C6: ='📊 DRE Mensal'!C21+'📊 DRE Mensal'!C28 -> 75093.1 | D6: ='📊 DRE Mensal'!D21+'📊 DRE Mensal'!D28 -> 81997.59 | E6: ='📊 DRE Mensal'!E21+'📊 DRE Mensal'!E28 -> 92749.06 | F6: ='📊 DRE Mensal'!F21+'📊 DRE Mensal'!F28 -> 95370.91 | G6: ='📊 DRE Mensal'!G21+'📊 DRE Mensal'!G28 -> 99619.95 | H6: ='📊 DRE Mensal'!H21+'📊 DRE Mensal'!H28 -> 105379.96 | I6: ='📊 DRE Mensal'!I21+'📊 DRE Mensal'!I28 -> 98501.01 | ... M6: ='📊 DRE Mensal'!M21+'📊 DRE Mensal'!M28 -> 122439.83 | N6: =SUM(B6:M6) -> 1147504.9
A7: 📊 EBITDA | B7: ='📊 DRE Mensal'!B29 -> 1963.6 | C7: ='📊 DRE Mensal'!C29 -> 594.99 | D7: ='📊 DRE Mensal'!D29 -> 5800.64 | E7: ='📊 DRE Mensal'!E29 -> 4879.81 | F7: ='📊 DRE Mensal'!F29 -> 3458.93 | G7: ='📊 DRE Mensal'!G29 -> 7145.21 | H7: ='📊 DRE Mensal'!H29 -> 1918.67 | I7: ='📊 DRE Mensal'!I29 -> 835.73 | ... M7: ='📊 DRE Mensal'!M29 -> 6791.3 | N7: =SUM(B7:M7) -> 38244.46
A8: 📉 Margem EBITDA (%) | B8: ='📊 DRE Mensal'!B30 -> 0.023678943 | C8: ='📊 DRE Mensal'!C30 -> 0.023678943 | D8: ='📊 DRE Mensal'!D30 -> 0.023678943 | E8: ='📊 DRE Mensal'!E30 -> 0.023678943 | F8: ='📊 DRE Mensal'!F30 -> 0.023678943 | G8: ='📊 DRE Mensal'!G30 -> 0.023678943 | H8: ='📊 DRE Mensal'!H30 -> 0.023678943 | I8: ='📊 DRE Mensal'!I30 -> 0.023678943 | ... M8: ='📊 DRE Mensal'!M30 -> 0.023678943 | N8: =SUM(B8:M8) -> 0.28414731
A9: 🧾 Custo com Pessoal | B9: ='📊 DRE Mensal'!B20 -> 26743.93 | C9: ='📊 DRE Mensal'!C20 -> 28000.43 | D9: ='📊 DRE Mensal'!D20 -> 30356.93 | E9: ='📊 DRE Mensal'!E20 -> 33870.29 | F9: ='📊 DRE Mensal'!F20 -> 35741.19 | G9: ='📊 DRE Mensal'!G20 -> 37322.37 | H9: ='📊 DRE Mensal'!H20 -> 39494.92 | I9: ='📊 DRE Mensal'!I20 -> 36411.5 | ... M9: ='📊 DRE Mensal'!M20 -> 44715.44 | N9: =SUM(B9:M9) -> 424904.43
A10: 🏗️ Custos Fixos (Infra) | B10: ='📊 DRE Mensal'!B25 -> 10975.48 | C10: ='📊 DRE Mensal'!C25 -> 11531.03 | D10: ='📊 DRE Mensal'!D25 -> 12658.48 | E10: ='📊 DRE Mensal'!E25 -> 14007.75 | F10: ='📊 DRE Mensal'!F25 -> 14419 | G10: ='📊 DRE Mensal'!G25 -> 15111.11 | H10: ='📊 DRE Mensal'!H25 -> 16181.95 | I10: ='📊 DRE Mensal'!I25 -> 14957.29 | ... M10: ='📊 DRE Mensal'!M25 -> 18350.53 | N10: =SUM(B10:M10) -> 174027.76
A12: ✅ STATUS DO MÊS | B12: =IF('📊 DRE Mensal'!B28>0,"✅ LUCRO","🔴 PREJUÍZO") -> ✅ LUCRO | C12: =IF('📊 DRE Mensal'!C28>0,"✅ LUCRO","🔴 PREJUÍZO") -> ✅ LUCRO | D12: =IF('📊 DRE Mensal'!D28>0,"✅ LUCRO","🔴 PREJUÍZO") -> ✅ LUCRO | E12: =IF('📊 DRE Mensal'!E28>0,"✅ LUCRO","🔴 PREJUÍZO") -> ✅ LUCRO | F12: =IF('📊 DRE Mensal'!F28>0,"✅ LUCRO","🔴 PREJUÍZO") -> ✅ LUCRO | G12: =IF('📊 DRE Mensal'!G28>0,"✅ LUCRO","🔴 PREJUÍZO") -> ✅ LUCRO | H12: =IF('📊 DRE Mensal'!H28>0,"✅ LUCRO","🔴 PREJUÍZO") -> ✅ LUCRO | I12: =IF('📊 DRE Mensal'!I28>0,"✅ LUCRO","🔴 PREJUÍZO") -> ✅ LUCRO | ... M12: =IF('📊 DRE Mensal'!M28>0,"✅ LUCRO","🔴 PREJUÍZO") -> ✅ LUCRO

Sheet 📈 Dashboard
A1: 📈 DASHBOARD FINANCEIRO — SABOR DE CASA 2024
A3: RECEITA TOTAL | D3: RESULTADO ANUAL | G3: MARGEM MÉDIA | J3: DESPESA TOTAL
A5: ='📊 DRE Mensal'!N9 -> 1323449 | D5: ='📊 DRE Mensal'!N29 -> 38244.46 | G5: =AVERAGE('🎯 Indicadores KPI'!B8:M8) -> 0.023678943 | J5: ='📊 DRE Mensal'!N21+'📊 DRE Mensal'!N28 -> 1147504.9
A10: Mês | B10: Receita | C10: Despesas | D10: Resultado | E10: Margem%
A11: Jan | B11: ='📊 DRE Mensal'!B9 -> 82926 | C11: ='📊 DRE Mensal'!B$28+'📊 DRE Mensal'!B$21 -> 72331.14 | D11: ='📊 DRE Mensal'!B$32 -> 1963.6 | E11: =IFERROR('📊 DRE Mensal'!B$29/'📊 DRE Mensal'!B$9,0) -> 0.023678943
A12: Fev | B12: ='📊 DRE Mensal'!C9 -> 84534 | C12: ='📊 DRE Mensal'!C$28+'📊 DRE Mensal'!C$21 -> 75093.1 | D12: ='📊 DRE Mensal'!C$32 -> 594.99 | E12: =IFERROR('📊 DRE Mensal'!C$29/'📊 DRE Mensal'!C$9,0) -> 0.0070384697
A13: Mar | B13: ='📊 DRE Mensal'!D9 -> 97722 | C13: ='📊 DRE Mensal'!D$28+'📊 DRE Mensal'!D$21 -> 81997.59 | D13: ='📊 DRE Mensal'!D$32 -> 5800.64 | E13: =IFERROR('📊 DRE Mensal'!D$29/'📊 DRE Mensal'!D$9,0) -> 0.059358589
A14: Abr | B14: ='📊 DRE Mensal'!E9 -> 108388 | C14: ='📊 DRE Mensal'!E$28+'📊 DRE Mensal'!E$21 -> 92749.06 | D14: ='📊 DRE Mensal'!E$32 -> 4879.81 | E14: =IFERROR('📊 DRE Mensal'!E$29/'📊 DRE Mensal'!E$9,0) -> 0.045021681
A15: Mai | B15: ='📊 DRE Mensal'!F9 -> 110071 | C15: ='📊 DRE Mensal'!F$28+'📊 DRE Mensal'!F$21 -> 95370.91 | D15: ='📊 DRE Mensal'!F$32 -> 3458.93 | E15: =IFERROR('📊 DRE Mensal'!F$29/'📊 DRE Mensal'!F$9,0) -> 0.031424535
A16: Jun | B16: ='📊 DRE Mensal'!G9 -> 118631 | C16: ='📊 DRE Mensal'!G$28+'📊 DRE Mensal'!G$21 -> 99619.95 | D16: ='📊 DRE Mensal'!G$32 -> 7145.21 | E16: =IFERROR('📊 DRE Mensal'!G$29/'📊 DRE Mensal'!G$9,0) -> 0.060230547
A17: Jul | B17: ='📊 DRE Mensal'!H9 -> 120257 | C17: ='📊 DRE Mensal'!H$28+'📊 DRE Mensal'!H$21 -> 105379.96 | D17: ='📊 DRE Mensal'!H$32 -> 1918.67 | E17: =IFERROR('📊 DRE Mensal'!H$29/'📊 DRE Mensal'!H$9,0) -> 0.015954747
A18: Ago | B18: ='📊 DRE Mensal'!I9 -> 111396 | C18: ='📊 DRE Mensal'!I$28+'📊 DRE Mensal'!I$21 -> 98501.01 | D18: ='📊 DRE Mensal'!I$32 -> 835.73 | E18: =IFERROR('📊 DRE Mensal'!I$29/'📊 DRE Mensal'!I$9,0) -> 0.007502334
A19: Set | B19: ='📊 DRE Mensal'!J9 -> 107448 | C19: ='📊 DRE Mensal'!J$28+'📊 DRE Mensal'!J$21 -> 93586.76 | D19: ='📊 DRE Mensal'!J$32 -> 2684.07 | E19: =IFERROR('📊 DRE Mensal'!J$29/'📊 DRE Mensal'!J$9,0) -> 0.024980176
A20: Out | B20: ='📊 DRE Mensal'!K9 -> 115762 | C20: ='📊 DRE Mensal'!K$28+'📊 DRE Mensal'!K$21 -> 102608.05 | D20: ='📊 DRE Mensal'!K$32 -> 896.79 | E20: =IFERROR('📊 DRE Mensal'!K$29/'📊 DRE Mensal'!K$9,0) -> 0.0077468427
A21: Nov | B21: ='📊 DRE Mensal'!L9 -> 122115 | C21: ='📊 DRE Mensal'!L$28+'📊 DRE Mensal'!L$21 -> 107827.58 | D21: ='📊 DRE Mensal'!L$32 -> 1274.72 | E21: =IFERROR('📊 DRE Mensal'!L$29/'📊 DRE Mensal'!L$9,0) -> 0.010438685
A22: Dez | B22: ='📊 DRE Mensal'!M9 -> 144199 | C22: ='📊 DRE Mensal'!M$28+'📊 DRE Mensal'!M$21 -> 122439.83 | D22: ='📊 DRE Mensal'!M$32 -> 6791.3 | E22: =IFERROR('📊 DRE Mensal'!M$29/'📊 DRE Mensal'!M$9,0) -> 0.047096721

Sheet 📖 Como Usar
A1: 📖 GUIA DE USO — SABOR DE CASA DASHBOARD
A3: 🏥 SOBRE ESTE PROJETO
A5: Este arquivo simula o sistema financeiro de um restaurante/food service, com dados de 2024.
A6: Criado como projeto de portfólio para demonstrar automação de planilhas financeiras.
A8: 📋 ABAS DO ARQUIVO
A10: 📋 Lançamentos → Base de dados com todas as receitas e despesas mensais.
A11: 📊 DRE Mensal → Demonstração do Resultado por mês com fórmulas automáticas.
A12: 🎯 Indicadores KPI → Principais métricas financeiras calculadas automaticamente.
A13: 📈 Dashboard → Visão gráfica e resumo executivo do desempenho anual.
A15: ✏️ COMO PERSONALIZAR
A17: 1. Acesse a aba '📋 Lançamentos' e altere os valores na coluna Valor (R$).
A18: 2. Todas as abas se atualizam automaticamente (DRE, KPI e Dashboard).
... A33: Projeto desenvolvido para demonstração de habilidades em Excel financeiro.
